AUTHORS.rst
CONTRIBUTING.rst
HISTORY.rst
LICENSE
MANIFEST.in
README.rst
setup.cfg
setup.py
docs/Makefile
docs/authors.rst
docs/conf.py
docs/contributing.rst
docs/history.rst
docs/index.rst
docs/installation.rst
docs/make.bat
docs/readme.rst
docs/usage.rst
pysurv_cmp1/__init__.py
pysurv_cmp1/pysurv_cmp1.py
pysurv_cmp1.egg-info/PKG-INFO
pysurv_cmp1.egg-info/SOURCES.txt
pysurv_cmp1.egg-info/dependency_links.txt
pysurv_cmp1.egg-info/not-zip-safe
pysurv_cmp1.egg-info/top_level.txt
tests/__init__.py
tests/test_pysurv_cmp1.py