Metadata-Version: 2.1
Name: pysurv-cmp1
Version: 0.1.1
Summary: Using Direct Method for estimate effect of covariates in Cumulative Incidnece Function
Home-page: https://github.com/stats9/pysurv_cmp1
Author: habib ezatabadi
Author-email: habibezati88@gmail.com
License: MIT license
Keywords: pysurv_cmp1
Classifier: Development Status :: 2 - Pre-Alpha
Classifier: Intended Audience :: Developers
Classifier: License :: OSI Approved :: MIT License
Classifier: Natural Language :: English
Classifier: Programming Language :: Python :: 3
Classifier: Programming Language :: Python :: 3.6
Classifier: Programming Language :: Python :: 3.7
Classifier: Programming Language :: Python :: 3.8
Requires-Python: >=3.6
License-File: LICENSE
License-File: AUTHORS.rst
